{
  "name": "no_mitigation",
  "data": [
    {
      "seriesName": "SBIORGAS02",
      "seriesValues": [
        [
          2018,
          0.312636689231243
        ],
        [
          2021,
          0.253364238334758
        ],
        [
          2022,
          0.312636689231243
        ],
        [
          2023,
          0.312636689231243
        ],
        [
          2024,
          0.312636689231243
        ],
        [
          2025,
          0.312636689231243
        ],
        [
          2026,
          0.312636689231243
        ],
        [
          2027,
          0.312636689231243
        ],
        [
          2028,
          0.0827296613426454
        ],
        [
          2029,
          0.312636689231243
        ],
        [
          2030,
          9.200936819935e-05
        ]
      ]
    },
    {
      "seriesName": "SBIORGAS05",
      "seriesValues": [
        [
          2018,
          0.0352215616074053
        ],
        [
          2020,
          0.0352215616074053
        ],
        [
          2021,
          0.0352215616074053
        ],
        [
          2022,
          0.0352215616074053
        ],
        [
          2023,
          0.0352215616074053
        ],
        [
          2024,
          0.0352215616074053
        ],
        [
          2025,
          0.0352215616074053
        ],
        [
          2026,
          0.0352215616074053
        ],
        [
          2027,
          0.0352215616074053
        ],
        [
          2028,
          0.0352215616074053
        ],
        [
          2029,
          0.0352215616074053
        ],
        [
          2030,
          0.0352215616074053
        ],
        [
          2031,
          0.0352215616074053
        ],
        [
          2032,
          0.0352215616074053
        ],
        [
          2035,
          0.0352215616074053
        ]
      ]
    },
    {
      "seriesName": "SBIORGAS06",
      "seriesValues": [
        [
          2018,
          0.060447597155688
        ],
        [
          2020,
          0.060447597155688
        ],
        [
          2021,
          0.060447597155688
        ],
        [
          2022,
          0.060447597155688
        ],
        [
          2023,
          0.060447597155688
        ],
        [
          2024,
          0.060447597155688
        ],
        [
          2025,
          0.060447597155688
        ],
        [
          2026,
          0.060447597155688
        ],
        [
          2027,
          0.060447597155688
        ],
        [
          2028,
          0.060447597155688
        ],
        [
          2029,
          0.060447597155688
        ],
        [
          2030,
          0.060447597155688
        ],
        [
          2031,
          0.060447597155688
        ],
        [
          2032,
          0.060447597155688
        ],
        [
          2035,
          0.060447597155688
        ]
      ]
    },
    {
      "seriesName": "SBIORGAS01",
      "seriesValues": [
        [
          2022,
          0.0634839388302295
        ],
        [
          2023,
          0.12980236178169
        ],
        [
          2024,
          0.887070006743868
        ],
        [
          2025,
          1.17908799137927
        ],
        [
          2026,
          1.43264053056519
        ],
        [
          2027,
          1.43264053056519
        ],
        [
          2028,
          1.36119274336492
        ],
        [
          2029,
          0.572030003464672
        ],
        [
          2030,
          0.0180946625452353
        ],
        [
          2031,
          0.019867119548742
        ],
        [
          2032,
          0.0215158093192506
        ],
        [
          2035,
          1.43264053056519
        ],
        [
          2040,
          1.4209196742795
        ],
        [
          2045,
          0.445333790553256
        ],
        [
          2050,
          0.14141978619583
        ]
      ]
    }
  ]
}