{
  "name": "no_mitigation",
  "data": [
    {
      "seriesName": "IMPBIODST1G_S1",
      "seriesValues": [
        [
          2018,
          4.36137696152625
        ]
      ]
    },
    {
      "seriesName": "IMPBIODST1G_S2",
      "seriesValues": [
        [
          2018,
          0.984514060783585
        ]
      ]
    },
    {
      "seriesName": "SBIORDST03",
      "seriesValues": [
        [
          2020,
          0.37687365979631
        ],
        [
          2021,
          0.37687365979631
        ],
        [
          2022,
          0.37687365979631
        ],
        [
          2023,
          0.37687365979631
        ],
        [
          2024,
          0.519334358913786
        ],
        [
          2025,
          0.521537874835213
        ],
        [
          2026,
          0.522018458300352
        ],
        [
          2027,
          0.522018458300352
        ],
        [
          2028,
          0.522018458300352
        ],
        [
          2029,
          0.522018458300352
        ],
        [
          2030,
          0.522018458300352
        ],
        [
          2031,
          0.522018458300352
        ],
        [
          2032,
          0.522018458300352
        ],
        [
          2035,
          0.522018458300352
        ],
        [
          2040,
          0.522018458300352
        ],
        [
          2045,
          0.439370978785757
        ],
        [
          2050,
          0.522018458300352
        ]
      ]
    },
    {
      "seriesName": "SBIORDST02",
      "seriesValues": [
        [
          2030,
          0.116503752627046
        ],
        [
          2031,
          0.116503752627046
        ],
        [
          2032,
          1.4311999248613
        ],
        [
          2035,
          7.83152949584773
        ],
        [
          2040,
          7.83152949584773
        ],
        [
          2045,
          7.83152949584773
        ],
        [
          2050,
          7.54882519604558
        ]
      ]
    }
  ]
}